{"components": [{"bom-ref": "crypto-protocol-tls-944f0560", "cryptoProperties": {"assetType": "protocol", "protocolProperties": {"cipherSuites": [{"algorithms": ["crypto-algo-TLS_AES_128_GCM_SHA256-944f0560"], "name": "TLS_AES_128_GCM_SHA256"}, {"algorithms": ["crypto-kex-X25519MLKEM768-944f0560"], "name": "X25519MLKEM768"}], "cryptoRefArray": ["crypto-algo-TLS_AES_128_GCM_SHA256-944f0560", "crypto-kex-X25519MLKEM768-944f0560"], "type": "tls", "version": "TLSv1.3"}}, "description": "TLS protocol configuration for digigodam.pnb.bank.in:443", "name": "TLS TLSv1.3 (digigodam.pnb.bank.in)", "type": "cryptographic-asset"}, {"bom-ref": "crypto-algo-TLS_AES_128_GCM_SHA256-944f0560", "cryptoProperties": {"algorithmProperties": {"nistQuantumSecurityLevel": 1, "parameterSetIdentifier": "None", "primitive": "unknown"}, "assetType": "algorithm"}, "description": "Cipher suite: TLS_AES_128_GCM_SHA256 (TLSv1.3)", "name": "TLS_AES_128_GCM_SHA256", "type": "cryptographic-asset"}, {"bom-ref": "crypto-kex-X25519MLKEM768-944f0560", "cryptoProperties": {"algorithmProperties": {"cryptoFunctions": ["keygen"], "nistQuantumSecurityLevel": 3, "primitive": "unknown"}, "assetType": "algorithm"}, "description": "Key exchange algorithm: X25519MLKEM768", "name": "X25519MLKEM768 Key Exchange", "type": "cryptographic-asset"}, {"bom-ref": "crypto-cert-0-944f0560", "cryptoProperties": {"assetType": "certificate", "certificateProperties": {"certificateFormat": "X.509", "issuerName": "GeoTrust EV RSA CA G2", "notValidAfter": "2026-09-03T23:59:59+00:00", "notValidBefore": "2025-09-04T00:00:00+00:00", "subjectName": "digigodam.pnb.bank.in"}}, "description": "X.509 certificate: digigodam.pnb.bank.in | RSA-2048 | Issuer: GeoTrust EV RSA CA G2", "name": "digigodam.pnb.bank.in (leaf)", "type": "cryptographic-asset"}], "dependencies": [{"ref": "crypto-algo-TLS_AES_128_GCM_SHA256-944f0560"}, {"ref": "crypto-cert-0-944f0560"}, {"ref": "crypto-kex-X25519MLKEM768-944f0560"}, {"ref": "crypto-protocol-tls-944f0560"}], "metadata": {"timestamp": "2026-04-13T21:39:20.677822+00:00"}, "serialNumber": "urn:uuid:7ddddb76-bed4-4ccc-a51d-2516aa30eca4", "version": 1, "$schema": "http://cyclonedx.org/schema/bom-1.6.schema.json", "bomFormat": "CycloneDX", "specVersion": "1.6"}